{
  "fetched_jst": "2026-03-26 05:07",
  "flights": [
    {
      "callsign": "VJC968",
      "lat": 26.9483,
      "lon": 122.8248,
      "alt_m": 10058.4,
      "speed_ms": 273.19,
      "heading": 45.08,
      "on_ground": false
    },
    {
      "callsign": "ABL712",
      "lat": 27.1051,
      "lon": 127.1778,
      "alt_m": 10058.4,
      "speed_ms": 236.5,
      "heading": 11.8,
      "on_ground": false
    },
    {
      "callsign": "JNA038",
      "lat": 27.3063,
      "lon": 126.6517,
      "alt_m": 11277.6,
      "speed_ms": 252.77,
      "heading": 21.87,
      "on_ground": false
    },
    {
      "callsign": "HKE676",
      "lat": 26.9722,
      "lon": 122.8389,
      "alt_m": 10668,
      "speed_ms": 277.92,
      "heading": 45.15,
      "on_ground": false
    },
    {
      "callsign": "THA682",
      "lat": 25.9543,
      "lon": 127.3063,
      "alt_m": 10668,
      "speed_ms": 294.06,
      "heading": 48.33,
      "on_ground": false
    },
    {
      "callsign": "TWB038",
      "lat": 25.6753,
      "lon": 122.6992,
      "alt_m": 10668,
      "speed_ms": 279.62,
      "heading": 49.78,
      "on_ground": false
    },
    {
      "callsign": "JA572A",
      "lat": 26.2551,
      "lon": 127.4169,
      "alt_m": 2979.42,
      "speed_ms": 139.78,
      "heading": 254.63,
      "on_ground": false
    },
    {
      "callsign": "PAL430",
      "lat": 25.9068,
      "lon": 127.5934,
      "alt_m": 10050.78,
      "speed_ms": 272.67,
      "heading": 36.33,
      "on_ground": false
    }
  ],
  "ships": [
    {
      "operator": "フェリーざまみ",
      "url": "https://www.vill.zamami.okinawa.jp/",
      "info": "2>本日の運航予定\r\n\t\r\n\t本日の運航予定はまだ公開されていません。\t<div style"
    },
    {
      "operator": "渡嘉敷村（マリンライナーとかしき）",
      "url": "https://www.vill.tokashiki.okinawa.jp/",
      "info": "村への代船運航のため運休となります。 / ため午後便欠航\t\t\t\t\t\t泊  港  発\t\t\t\t\t\t09：00                                       \t\t\t16：30 (欠航)\t\t\t\t\t\t\t\t\t\t渡嘉敷港発\t\t"
    }
  ]
}