{
  "fetched_jst": "2026-04-05 09:01",
  "flights": [
    {
      "callsign": "JAL901",
      "lat": 26.6028,
      "lon": 128.0308,
      "alt_m": 4023.36,
      "speed_ms": 167.79,
      "heading": 204.84,
      "on_ground": false
    },
    {
      "callsign": "CAL154",
      "lat": 25.8178,
      "lon": 122.5504,
      "alt_m": 8793.48,
      "speed_ms": 243.85,
      "heading": 56.88,
      "on_ground": false
    },
    {
      "callsign": "SJX846",
      "lat": 25.8604,
      "lon": 122.6643,
      "alt_m": 8778.24,
      "speed_ms": 242.42,
      "heading": 56.07,
      "on_ground": false
    },
    {
      "callsign": "OCTNE91",
      "lat": 26.3508,
      "lon": 127.7643,
      "alt_m": null,
      "speed_ms": 13.38,
      "heading": 230.62,
      "on_ground": true
    },
    {
      "callsign": "CEB185",
      "lat": 25.7852,
      "lon": 127.1446,
      "alt_m": 9768.84,
      "speed_ms": 205.62,
      "heading": 193.9,
      "on_ground": false
    },
    {
      "callsign": "HVN441",
      "lat": 25.6941,
      "lon": 122.5837,
      "alt_m": 9753.6,
      "speed_ms": 231.03,
      "heading": 200.74,
      "on_ground": false
    },
    {
      "callsign": "APJ375",
      "lat": 28.4919,
      "lon": 128.5133,
      "alt_m": 11567.16,
      "speed_ms": 183.02,
      "heading": 218.61,
      "on_ground": false
    },
    {
      "callsign": "APJ209",
      "lat": 26.2023,
      "lon": 127.8006,
      "alt_m": 1744.98,
      "speed_ms": 131.47,
      "heading": 197.3,
      "on_ground": false
    },
    {
      "callsign": "SKY511",
      "lat": 26.857,
      "lon": 128.1127,
      "alt_m": 5463.54,
      "speed_ms": 167.85,
      "heading": 212.23,
      "on_ground": false
    }
  ],
  "ships": [
    {
      "operator": "フェリーざまみ",
      "url": "https://www.vill.zamami.okinawa.jp/",
      "info": "運休"
    },
    {
      "operator": "渡嘉敷村（マリンライナーとかしき）",
      "url": "https://www.vill.tokashiki.okinawa.jp/",
      "info": "村への代船運航のため運休となります。 / き」ドック運休予定令和8年5月18日(月曜日)～5月28日(木曜日)＜ドック準備の為5月17日の2便目は運休予定＞      \" />  <meta name=\"viewport\" content=\""
    }
  ]
}