{
  "fetched_jst": "2026-03-21 08:56",
  "flights": [
    {
      "callsign": "OAE280",
      "lat": 26.3507,
      "lon": 127.7642,
      "alt_m": null,
      "speed_ms": 12.35,
      "heading": 230.62,
      "on_ground": true
    },
    {
      "callsign": "CPA086",
      "lat": 27.98,
      "lon": 125.7897,
      "alt_m": 10058.4,
      "speed_ms": 289.1,
      "heading": 50.56,
      "on_ground": false
    },
    {
      "callsign": "EVA182",
      "lat": 25.6392,
      "lon": 122.6515,
      "alt_m": 10668,
      "speed_ms": 278.56,
      "heading": 49.87,
      "on_ground": false
    },
    {
      "callsign": "JJA2121",
      "lat": 26.8352,
      "lon": 127.4198,
      "alt_m": 10972.8,
      "speed_ms": 201.83,
      "heading": 196.59,
      "on_ground": false
    },
    {
      "callsign": "CAL164",
      "lat": 26.8224,
      "lon": 122.6222,
      "alt_m": 10668,
      "speed_ms": 250.93,
      "heading": 35.32,
      "on_ground": false
    },
    {
      "callsign": "SJX834",
      "lat": 28.2243,
      "lon": 126.1253,
      "alt_m": 9448.8,
      "speed_ms": 257.28,
      "heading": 50.52,
      "on_ground": false
    },
    {
      "callsign": "CATS81",
      "lat": 28.2023,
      "lon": 127.7245,
      "alt_m": 7620,
      "speed_ms": 136.06,
      "heading": 3.47,
      "on_ground": false
    },
    {
      "callsign": "SJX846",
      "lat": 25.7026,
      "lon": 122.5432,
      "alt_m": 7696.2,
      "speed_ms": 224.41,
      "heading": 53.58,
      "on_ground": false
    },
    {
      "callsign": "JAL901",
      "lat": 26.859,
      "lon": 128.0021,
      "alt_m": 5059.68,
      "speed_ms": 189.23,
      "heading": 188.28,
      "on_ground": false
    },
    {
      "callsign": "PAL401",
      "lat": 27.2297,
      "lon": 127.5427,
      "alt_m": 10370.82,
      "speed_ms": 216.35,
      "heading": 194.04,
      "on_ground": false
    },
    {
      "callsign": "PAL487",
      "lat": 25.8301,
      "lon": 127.0247,
      "alt_m": 10347.96,
      "speed_ms": 209.1,
      "heading": 195.85,
      "on_ground": false
    },
    {
      "callsign": "CEB5064",
      "lat": 27.2329,
      "lon": 129.0673,
      "alt_m": 10652.76,
      "speed_ms": 275.17,
      "heading": 46.97,
      "on_ground": false
    },
    {
      "callsign": "ANA993",
      "lat": 27.7036,
      "lon": 128.9326,
      "alt_m": 8526.78,
      "speed_ms": 213.96,
      "heading": 231.84,
      "on_ground": false
    },
    {
      "callsign": "TORI11",
      "lat": 26.7383,
      "lon": 128.3428,
      "alt_m": 5440.68,
      "speed_ms": 116.27,
      "heading": 53.64,
      "on_ground": false
    },
    {
      "callsign": "SKY511",
      "lat": 27.8658,
      "lon": 129.1404,
      "alt_m": 10972.8,
      "speed_ms": 172.99,
      "heading": 222.23,
      "on_ground": false
    },
    {
      "callsign": "APJ859",
      "lat": 28.0899,
      "lon": 125.3655,
      "alt_m": 11590.02,
      "speed_ms": 187.61,
      "heading": 230.9,
      "on_ground": false
    },
    {
      "callsign": "APJ209",
      "lat": 26.6765,
      "lon": 127.958,
      "alt_m": 4069.08,
      "speed_ms": 179.66,
      "heading": 196.98,
      "on_ground": false
    },
    {
      "callsign": "JAL971",
      "lat": 27.3424,
      "lon": 127.9855,
      "alt_m": 8534.4,
      "speed_ms": 223.76,
      "heading": 229.76,
      "on_ground": false
    },
    {
      "callsign": "ANA461",
      "lat": 27.5619,
      "lon": 128.7258,
      "alt_m": 10972.8,
      "speed_ms": 188.57,
      "heading": 231.54,
      "on_ground": false
    },
    {
      "callsign": "APJ469",
      "lat": 27.8801,
      "lon": 127.958,
      "alt_m": 10980.42,
      "speed_ms": 198.71,
      "heading": 217.85,
      "on_ground": false
    },
    {
      "callsign": "N55246",
      "lat": 26.373,
      "lon": 127.7672,
      "alt_m": 190.5,
      "speed_ms": 52.24,
      "heading": 302.12,
      "on_ground": false
    }
  ],
  "ships": [
    {
      "operator": "フェリーざまみ",
      "url": "https://www.vill.zamami.okinawa.jp/",
      "info": "2>本日の運航予定\r\n\t\r\n\t\t\r\n\t\r\n\t3月21日(土）くもり昼前から昼過ぎ雨　フェリーざまみ３及びクイーンざまみは予定どおり運航します。お乗りにな / になる船の出港時間を確認し、出港10分前までにご乗船下さい。朝の渋滞・駐車場満車で乗り遅れる方がいらしゃいます。時間に余裕を持って、乗船いただきますようお願い致します。\t\r\n\t\r\n\t\r\n\t\t<div "
    },
    {
      "operator": "渡嘉敷村（マリンライナーとかしき）",
      "url": "https://www.vill.tokashiki.okinawa.jp/",
      "info": "村への代船運航のため運休となります。 / き」ドック運休予定令和8年5月18日(月曜日)～5月28日(木曜日)      \" />        <meta name=\""
    }
  ]
}