{
  "fetched_jst": "2026-03-31 13:05",
  "flights": [
    {
      "callsign": "JTA610",
      "lat": 26.6033,
      "lon": 127.347,
      "alt_m": 1203.96,
      "speed_ms": 115.86,
      "heading": 48.24,
      "on_ground": false
    },
    {
      "callsign": "MAS067",
      "lat": 26.1565,
      "lon": 127.5036,
      "alt_m": 10972.8,
      "speed_ms": 226.7,
      "heading": 200.04,
      "on_ground": false
    },
    {
      "callsign": "CPA536",
      "lat": 25.6897,
      "lon": 122.7173,
      "alt_m": 12496.8,
      "speed_ms": 268.29,
      "heading": 49.74,
      "on_ground": false
    },
    {
      "callsign": "ANA1883",
      "lat": 26.3786,
      "lon": 127.2632,
      "alt_m": 1790.7,
      "speed_ms": 106.31,
      "heading": 332.32,
      "on_ground": false
    },
    {
      "callsign": "ANA1207",
      "lat": 26.6065,
      "lon": 127.9453,
      "alt_m": 3337.56,
      "speed_ms": 114.79,
      "heading": 210.13,
      "on_ground": false
    },
    {
      "callsign": "ANA1080",
      "lat": 27.0863,
      "lon": 128.4486,
      "alt_m": 12489.18,
      "speed_ms": 282.71,
      "heading": 34.85,
      "on_ground": false
    },
    {
      "callsign": "THA649",
      "lat": 27.6405,
      "lon": 126.7178,
      "alt_m": 10363.2,
      "speed_ms": 220.16,
      "heading": 236.53,
      "on_ground": false
    },
    {
      "callsign": "THA645",
      "lat": 26.4247,
      "lon": 127.1923,
      "alt_m": 12184.38,
      "speed_ms": 222.47,
      "heading": 215.97,
      "on_ground": false
    },
    {
      "callsign": "TWB281",
      "lat": 27.0488,
      "lon": 127.7505,
      "alt_m": 4434.84,
      "speed_ms": 126.62,
      "heading": 231.27,
      "on_ground": false
    },
    {
      "callsign": "PAL426",
      "lat": 26.1915,
      "lon": 127.3876,
      "alt_m": 12496.8,
      "speed_ms": 270.23,
      "heading": 29.54,
      "on_ground": false
    },
    {
      "callsign": "ANA1867",
      "lat": 26.5653,
      "lon": 127.3631,
      "alt_m": 2880.36,
      "speed_ms": 110.17,
      "heading": 258.69,
      "on_ground": false
    },
    {
      "callsign": "JTA558",
      "lat": 26.5708,
      "lon": 127.6408,
      "alt_m": 899.16,
      "speed_ms": 103.51,
      "heading": 186.28,
      "on_ground": false
    },
    {
      "callsign": "JAL2084",
      "lat": 27.8386,
      "lon": 127.9399,
      "alt_m": 10020.3,
      "speed_ms": 246.72,
      "heading": 41.53,
      "on_ground": false
    },
    {
      "callsign": "ANA1861",
      "lat": 27.5299,
      "lon": 128.0173,
      "alt_m": 6713.22,
      "speed_ms": 172.49,
      "heading": 211.46,
      "on_ground": false
    },
    {
      "callsign": "JNA358",
      "lat": 26.4215,
      "lon": 128.2131,
      "alt_m": 10668,
      "speed_ms": 255.34,
      "heading": 23.26,
      "on_ground": false
    },
    {
      "callsign": "TGW820",
      "lat": 26.13,
      "lon": 126.987,
      "alt_m": 11887.2,
      "speed_ms": 277.19,
      "heading": 37.23,
      "on_ground": false
    },
    {
      "callsign": "SKY163",
      "lat": 26.8269,
      "lon": 125.962,
      "alt_m": 10363.2,
      "speed_ms": 215.45,
      "heading": 236.69,
      "on_ground": false
    },
    {
      "callsign": "ANA806",
      "lat": 27.9597,
      "lon": 129.372,
      "alt_m": 11879.58,
      "speed_ms": 281.61,
      "heading": 50.93,
      "on_ground": false
    }
  ],
  "ships": [
    {
      "operator": "フェリーざまみ",
      "url": "https://www.vill.zamami.okinawa.jp/",
      "info": "まみは全便欠航となりました、フェリーざまみは予定通りの運航です。 / 運休"
    },
    {
      "operator": "渡嘉敷村（マリンライナーとかしき）",
      "url": "https://www.vill.tokashiki.okinawa.jp/",
      "info": "村への代船運航のため運休となります。 / のため全便欠航(Cancelled)\t\t\t\t\t\t泊  港  発\t\t\t\t\t\t09：00 (欠航)                                 \t\t\t16：30 (欠航)\t\t\t\t\t\t\t"
    }
  ]
}