{
  "fetched_jst": "2026-03-22 08:30",
  "flights": [
    {
      "callsign": "ANA460",
      "lat": 27.3431,
      "lon": 129.2896,
      "alt_m": 10386.06,
      "speed_ms": 296.5,
      "heading": 47.95,
      "on_ground": false
    },
    {
      "callsign": "JAL901",
      "lat": 27.8976,
      "lon": 129.2547,
      "alt_m": 10363.2,
      "speed_ms": 219.98,
      "heading": 232.89,
      "on_ground": false
    },
    {
      "callsign": "EVA158",
      "lat": 28.3511,
      "lon": 126.3016,
      "alt_m": 9448.8,
      "speed_ms": 259.27,
      "heading": 50.88,
      "on_ground": false
    },
    {
      "callsign": "TTW236",
      "lat": 27.9775,
      "lon": 125.7857,
      "alt_m": 10660.38,
      "speed_ms": 274.87,
      "heading": 50.62,
      "on_ground": false
    },
    {
      "callsign": "EVA110",
      "lat": 28.265,
      "lon": 126.1815,
      "alt_m": 8839.2,
      "speed_ms": 263.62,
      "heading": 50.78,
      "on_ground": false
    },
    {
      "callsign": "ANA1201",
      "lat": 26.79,
      "lon": 127.917,
      "alt_m": 2796.54,
      "speed_ms": 141.25,
      "heading": 211.14,
      "on_ground": false
    },
    {
      "callsign": "CAL112",
      "lat": 25.8225,
      "lon": 122.7593,
      "alt_m": 8115.3,
      "speed_ms": 254.55,
      "heading": 52.97,
      "on_ground": false
    },
    {
      "callsign": "SJX834",
      "lat": 27.9849,
      "lon": 125.796,
      "alt_m": 10660.38,
      "speed_ms": 265.94,
      "heading": 51.05,
      "on_ground": false
    },
    {
      "callsign": "TAX602",
      "lat": 26.935,
      "lon": 128.698,
      "alt_m": 11887.2,
      "speed_ms": 269.7,
      "heading": 46.93,
      "on_ground": false
    },
    {
      "callsign": "TAX630",
      "lat": 26.7674,
      "lon": 128.4789,
      "alt_m": 11277.6,
      "speed_ms": 278.83,
      "heading": 47.09,
      "on_ground": false
    },
    {
      "callsign": "EOK394",
      "lat": 27.2774,
      "lon": 127.9906,
      "alt_m": 5791.2,
      "speed_ms": 192.48,
      "heading": 199.36,
      "on_ground": false
    },
    {
      "callsign": "JAL38",
      "lat": 27.5211,
      "lon": 129.4242,
      "alt_m": 11277.6,
      "speed_ms": 282.12,
      "heading": 47.14,
      "on_ground": false
    },
    {
      "callsign": "CEB5068",
      "lat": 26.836,
      "lon": 128.5901,
      "alt_m": 10058.4,
      "speed_ms": 268.05,
      "heading": 47.8,
      "on_ground": false
    },
    {
      "callsign": "APJ921",
      "lat": 25.979,
      "lon": 127.3672,
      "alt_m": 4914.9,
      "speed_ms": 167.81,
      "heading": 259.76,
      "on_ground": false
    },
    {
      "callsign": "ANA856",
      "lat": 27.7753,
      "lon": 129.7013,
      "alt_m": 12496.8,
      "speed_ms": 294.22,
      "heading": 47.55,
      "on_ground": false
    },
    {
      "callsign": "APJ774",
      "lat": 26.712,
      "lon": 126.9915,
      "alt_m": 10683.24,
      "speed_ms": 261.52,
      "heading": 35.47,
      "on_ground": false
    }
  ],
  "ships": [
    {
      "operator": "フェリーざまみ",
      "url": "https://www.vill.zamami.okinawa.jp/",
      "info": "2>本日の運航予定\r\n\t\r\n\t\t\r\n\t\r\n\t3月22日(日）晴れ時々くもり所により雨　フェリーざまみ３及びクイーンざまみは予定どおり運航します。お乗りに / になる船の出港時間を確認し、出港10分前までにご乗船下さい。朝の渋滞・駐車場満車で乗り遅れる方がいらしゃいます。時間に余裕を持って、乗船いただきますようお願い致します。\t\r\n\t\r\n\t\r\n\t\t<div "
    },
    {
      "operator": "渡嘉敷村（マリンライナーとかしき）",
      "url": "https://www.vill.tokashiki.okinawa.jp/",
      "info": "村への代船運航のため運休となります。 / き」ドック運休予定令和8年5月18日(月曜日)～5月28日(木曜日)      \" />        <meta name=\""
    }
  ]
}